LICENSE
README.md
setup.py
torchdynamo/__init__.py
torchdynamo/_eval_frame.c
torchdynamo/_guards.cpp
torchdynamo/allowed_functions.py
torchdynamo/bytecode_analysis.py
torchdynamo/bytecode_transformation.py
torchdynamo/codegen.py
torchdynamo/config.py
torchdynamo/convert_frame.py
torchdynamo/debug_utils.py
torchdynamo/eval_frame.py
torchdynamo/exc.py
torchdynamo/guards.py
torchdynamo/logging.py
torchdynamo/mutation_guard.py
torchdynamo/output_graph.py
torchdynamo/profiler.py
torchdynamo/replay_record.py
torchdynamo/resume_execution.py
torchdynamo/side_effects.py
torchdynamo/skipfiles.py
torchdynamo/source.py
torchdynamo/symbolic_convert.py
torchdynamo/testing.py
torchdynamo/utils.py
torchdynamo.egg-info/PKG-INFO
torchdynamo.egg-info/SOURCES.txt
torchdynamo.egg-info/dependency_links.txt
torchdynamo.egg-info/not-zip-safe
torchdynamo.egg-info/requires.txt
torchdynamo.egg-info/top_level.txt
torchdynamo/optimizations/__init__.py
torchdynamo/optimizations/analysis.py
torchdynamo/optimizations/backends.py
torchdynamo/optimizations/distributed.py
torchdynamo/optimizations/inference.py
torchdynamo/optimizations/log_args.py
torchdynamo/optimizations/normalize.py
torchdynamo/optimizations/subgraph.py
torchdynamo/optimizations/training.py
torchdynamo/variables/__init__.py
torchdynamo/variables/base.py
torchdynamo/variables/builder.py
torchdynamo/variables/builtin.py
torchdynamo/variables/constant.py
torchdynamo/variables/dicts.py
torchdynamo/variables/functions.py
torchdynamo/variables/lists.py
torchdynamo/variables/misc.py
torchdynamo/variables/nn_module.py
torchdynamo/variables/tensor.py
torchdynamo/variables/torch.py
torchdynamo/variables/user_defined.py
torchinductor/__init__.py
torchinductor/codecache.py
torchinductor/compile_fx.py
torchinductor/config.py
torchinductor/debug.py
torchinductor/decomposition.py
torchinductor/dependencies.py
torchinductor/exc.py
torchinductor/graph.py
torchinductor/ir.py
torchinductor/lowering.py
torchinductor/metrics.py
torchinductor/overrides.py
torchinductor/scheduler.py
torchinductor/sizevars.py
torchinductor/utils.py
torchinductor/virtualized.py
torchinductor/codegen/__init__.py
torchinductor/codegen/autotuner.py
