Metadata-Version: 2.1
Name: torchdynamo
Version: 1.13.0
Summary: A Python-level JIT compiler designed to make unmodified PyTorch programs faster.
Home-page: https://github.com/pytorch/torchdynamo
Author: Jason Ansel
Author-email: jansel@fb.com
License: BSD-3
Keywords: pytorch machine learning compilers
Requires-Python: >=3.7, <3.11
License-File: LICENSE
